tcafe_attending_bot/__init__.py
tcafe_attending_bot/__main__.py
tcafe_attending_bot/py.typed
tcafe_attending_bot-1.0.0.dist-info/entry_points.txt
tcafe_attending_bot-1.0.0.dist-info/LICENSE
tcafe_attending_bot-1.0.0.dist-info/WHEEL
tcafe_attending_bot-1.0.0.dist-info/METADATA
tcafe_attending_bot-1.0.0.dist-info/RECORD
