Metadata-Version: 2.1
Name: tcafe-attending-bot
Version: 1.0.0
Summary: Auto attending bot for TCafe.
Author-email: Byeonghoon Yoo <bhyoo@bhyoo.com>
Requires-Python: >3.10
Classifier: Development Status :: 5 - Production/Stable
Classifier: Framework :: AsyncIO
Classifier: Environment :: Console
Classifier: Intended Audience :: End Users/Desktop
Classifier: License :: OSI Approved :: MIT License
Classifier: Natural Language :: Korean
Classifier: Operating System :: OS Independent
Classifier: Programming Language :: Python
Classifier: Programming Language :: Python :: 3
Classifier: Programming Language :: Python :: 3.10
Classifier: Programming Language :: Python :: 3.11
Classifier: Programming Language :: Python :: 3.12
Classifier: Programming Language :: Python :: 3 :: Only
Classifier: Typing :: Typed
Requires-Dist: aiohttp==3.8.5
Requires-Dist: beautifulsoup4==4.12.2
Requires-Dist: xdg-base-dirs==6.0.0
Requires-Dist: black ; extra == "lint"
Requires-Dist: pytest ; extra == "test"
Requires-Dist: pytest-asyncio ; extra == "test"
Project-URL: Home, https://github.com/isac322/tcafe-attending-bot
Provides-Extra: lint
Provides-Extra: test
